Metadata-Version: 2.1
Name: fine-tune
Version: 0.0.0
Summary: Jina is the cloud-native neural search framework for any kind of data
Home-page: https://github.com/jina-ai/jina/
Author: Jina AI
Author-email: hello@jina.ai
License: Apache 2.0
Download-URL: https://github.com/jina-ai/jina/tags
Project-URL: Documentation, https://docs.jina.ai
Project-URL: Source, https://github.com/jina-ai/jina/
Project-URL: Tracker, https://github.com/jina-ai/jina/issues
Keywords: jina cloud-native neural-search query search index elastic neural-network encoding embedding serving docker container image video audio deep-learning
Platform: UNKNOWN
Classifier: Development Status :: 5 - Production/Stable
Classifier: Intended Audience :: Developers
Classifier: Intended Audience :: Education
Classifier: Intended Audience :: Science/Research
Classifier: Programming Language :: Python :: 3.7
Classifier: Programming Language :: Python :: 3.8
Classifier: Programming Language :: Python :: 3.9
Classifier: Programming Language :: Unix Shell
Classifier: Environment :: Console
Classifier: License :: OSI Approved :: Apache Software License
Classifier: Operating System :: OS Independent
Classifier: Topic :: Database :: Database Engines/Servers
Classifier: Topic :: Scientific/Engineering :: Artificial Intelligence
Classifier: Topic :: Internet :: WWW/HTTP :: Indexing/Search
Classifier: Topic :: Scientific/Engineering :: Image Recognition
Classifier: Topic :: Multimedia :: Video
Classifier: Topic :: Scientific/Engineering
Classifier: Topic :: Scientific/Engineering :: Mathematics
Classifier: Topic :: Software Development
Classifier: Topic :: Software Development :: Libraries
Classifier: Topic :: Software Development :: Libraries :: Python Modules
Provides-Extra: scipy
Provides-Extra: devel
Provides-Extra: fastapi
Provides-Extra: standard
Provides-Extra: demo
Provides-Extra: daemon
Provides-Extra: uvicorn[standard]
Provides-Extra: fluent-logger
Provides-Extra: docker
Provides-Extra: pathspec
Provides-Extra: rich
Provides-Extra: cryptography
Provides-Extra: filelock
Provides-Extra: requests
Provides-Extra: torch
Provides-Extra: transformers
Provides-Extra: cicd
Provides-Extra: tensorflow
Provides-Extra: torchvision
Provides-Extra: Pillow
Provides-Extra: lz4
Provides-Extra: perf
Provides-Extra: uvloop
Provides-Extra: core
Provides-Extra: numpy
Provides-Extra: pyzmq
Provides-Extra: protobuf
Provides-Extra: grpcio
Provides-Extra: pyyaml
Provides-Extra: tornado
Provides-Extra: test
Provides-Extra: pytest
Provides-Extra: pytest-timeout
Provides-Extra: pytest-mock
Provides-Extra: pytest-cov
Provides-Extra: pytest-repeat
Provides-Extra: pytest-asyncio
Provides-Extra: pytest-reraise
Provides-Extra: flaky
Provides-Extra: mock
Provides-Extra: prettytable
Provides-Extra: optuna
Provides-Extra: websockets
Provides-Extra: pydantic
Provides-Extra: python-multipart
Provides-Extra: aiofiles
Provides-Extra: aiohttp
Provides-Extra: pytest-custom_exit_code
Provides-Extra: bs4
Provides-Extra: aiostream
Provides-Extra: jsonschema
Provides-Extra: dgl
Provides-Extra: black
Provides-Extra: matplotlib
Provides-Extra: all
